airboss/__init__.py
airboss/ui/cli/main.py
airboss-0.2.1.dist-info/LICENSE
airboss-0.2.1.dist-info/METADATA
airboss-0.2.1.dist-info/WHEEL
airboss-0.2.1.dist-info/entry_points.txt
airboss-0.2.1.dist-info/RECORD
